mixed_pickles-0.2.1.dist-info/METADATA
mixed_pickles-0.2.1.dist-info/WHEEL
mixed_pickles-0.2.1.dist-info/entry_points.txt
mixed_pickles-0.2.1.dist-info/licenses/LICENSE
mixed_pickles/__init__.py
mixed_pickles/mixed_pickles.abi3.so
mixed_pickles-0.2.1.dist-info/RECORD
