Metadata-Version: 2.4
Name: mixed-pickles
Version: 0.2.1
Classifier: Development Status :: 4 - Beta
Classifier: Environment :: Console
Classifier: Intended Audience :: Developers
Classifier: License :: OSI Approved :: MIT License
Classifier: Programming Language :: Python :: 3
Classifier: Programming Language :: Python :: 3.9
Classifier: Programming Language :: Python :: 3.10
Classifier: Programming Language :: Python :: 3.11
Classifier: Programming Language :: Python :: 3.12
Classifier: Programming Language :: Python :: 3.13
Classifier: Programming Language :: Rust
Classifier: Topic :: Software Development :: Quality Assurance
Classifier: Topic :: Software Development :: Version Control :: Git
Requires-Dist: pytest>=7.0 ; extra == 'dev'
Requires-Dist: maturin>=1.0,<2.0 ; extra == 'dev'
Provides-Extra: dev
License-File: LICENSE
Summary: A fast git commit message linter written in Rust
Keywords: git,commit,linter,conventional-commits,rust
Author-email: Denny Rommel <rommel.denny@gmail.com>
License-Expression: MIT
Requires-Python: >=3.9
Project-URL: Repository, https://github.com/rommeld/mixed-pickles
Project-URL: Changelog, https://github.com/rommeld/mixed-pickles/blob/main/CHANGELOG.md
Project-URL: Issues, https://github.com/rommeld/mixed-pickles/issues
